file_of_test_of_wangziming/__init__.py
file_of_test_of_wangziming/__main__.py
file_of_test_of_wangziming/file_of_test.py
file_of_test_of_wangziming/data/text.txt
file_of_test_of_wangziming-0.0.11.dist-info/LICENSE
file_of_test_of_wangziming-0.0.11.dist-info/METADATA
file_of_test_of_wangziming-0.0.11.dist-info/WHEEL
file_of_test_of_wangziming-0.0.11.dist-info/entry_points.txt
file_of_test_of_wangziming-0.0.11.dist-info/top_level.txt
file_of_test_of_wangziming-0.0.11.dist-info/RECORD
